zolldo/__init__.py
zolldo/zolldo.py
zolldo-1.3.dist-info/LICENSE
zolldo-1.3.dist-info/METADATA
zolldo-1.3.dist-info/WHEEL
zolldo-1.3.dist-info/entry_points.txt
zolldo-1.3.dist-info/top_level.txt
zolldo-1.3.dist-info/RECORD
