Metadata-Version: 2.2
Name: zolldo
Version: 1.3
Summary: A lightweight to-do list.
Author-email: Caleb Aikens <zollqir@gmail.com>
Project-URL: Homepage, https://github.com/zollqir/zolldo
Project-URL: Issues, https://github.com/zollqir/zolldo/issues
Classifier: Programming Language :: Python :: 3.10
Classifier: Operating System :: OS Independent
Classifier: License :: OSI Approved :: GNU General Public License v3 (GPLv3)
Classifier: Natural Language :: English
Requires-Python: >=3.10
License-File: LICENSE
